Metadata-Version: 2.1
Name: tensorutils
Version: 0.0.2
Summary: Small utils for Tensorflow in Python.
Home-page: https://github.com/jmgomezsoriano/tensorutils
Author: José Manuel Gómez Soriano
Author-email: jmgomez.soriano@gmail.com
License: LGPL3
Platform: UNKNOWN
Classifier: Programming Language :: Python :: 3
Classifier: License :: OSI Approved :: MIT License
Classifier: Operating System :: OS Independent
Requires-Python: >=3.7
